Metadata-Version: 2.4
Name: x_make_markdown_x
Version: 12.0.0
Summary: Makes markdown.
Author-email: RRGM of the Primus Pilus Night Watch AI Corporation <eye4357@outlook.com>
License-Expression: MIT
Requires-Dist: markdown
Requires-Dist: pdfkit
